google_assistant_sdk-0.6.0-py3.5-nspkg.pth
googlesamples/assistant/grpc/__init__.py
googlesamples/assistant/grpc/assistant_helpers.py
googlesamples/assistant/grpc/audio_helpers.py
googlesamples/assistant/grpc/audiofileinput.py
googlesamples/assistant/grpc/browser_helpers.py
googlesamples/assistant/grpc/device_helpers.py
googlesamples/assistant/grpc/devicetool.py
googlesamples/assistant/grpc/pushtotalk.py
googlesamples/assistant/grpc/textinput.py
google_assistant_sdk-0.6.0.dist-info/LICENSE
google_assistant_sdk-0.6.0.dist-info/METADATA
google_assistant_sdk-0.6.0.dist-info/WHEEL
google_assistant_sdk-0.6.0.dist-info/entry_points.txt
google_assistant_sdk-0.6.0.dist-info/namespace_packages.txt
google_assistant_sdk-0.6.0.dist-info/top_level.txt
google_assistant_sdk-0.6.0.dist-info/RECORD
